Workbook

Sheet Assumptions
A1: WACC BUILD
A3: Risk-free rate (10Y AGB) | B3: 0.025
A4: Equity risk premium | B4: 0.065
A5: Beta (levered) | B5: 1.1
A6: Cost of equity (CAPM) | B6: =B3+B5*B4
A8: Pre-tax cost of debt | B8: 0.05
A9: Tax rate | B9: 0.17
A10: After-tax cost of debt | B10: =B8*(1-B9)
A12: Market value of equity ($m) | B12: 328.35
A13: Market value of debt ($m) | B13: 84.62
A14: Enterprise value ($m) | B14: =B12+B13
A15: Equity weight (E/V) | B15: =B12/B14
A16: Debt weight (D/V) | B16: =B13/B14
A17: WACC | B17: =B15*B6+B16*B10
A20: P&L DRIVERS
A22: Year | B22: FY20 | C22: FY21 | D22: FY22 | E22: FY23 | F22: FY24 | G22: FY25 | H22: FY26 | I22: FY27 | J22: FY28 | K22: FY29 | L22: FY30
A23: Revenue growth % | C23: 0.0926 | D23: 0.0782 | E23: 0.0688 | F23: -0.003 | G23: 0.02 | H23: 0.018 | I23: 0.016 | J23: 0.014 | K23: 0.012 | L23: 0.01
A24: EBITDA margin % | B24: 0.082 | C24: 0.074 | D24: 0.083 | E24: 0.086 | F24: 0.088 | G24: 0.089 | H24: 0.089 | I24: 0.089 | J24: 0.09 | K24: 0.09 | L24: 0.09
A25: D&A ($m) | B25: -36.1 | C25: -40.5 | D25: -47.2 | E25: -51.8 | F25: -54.8 | G25: -53.6 | H25: -52.4 | I25: -51.2 | J25: -49.9 | K25: -48.7 | L25: -47.5
A26: Capex ($m) | B26: -36 | C26: -51 | D26: -50 | E26: -50 | F26: -50 | G26: -50 | H26: -50 | I26: -50 | J26: -50 | K26: -50 | L26: -50
A27: Change in working capital ($m) | B27: 6 | C27: 16.1 | D27: 15.2 | E27: 11.1 | F27: 4 | G27: 1 | H27: 1 | I27: 1 | J27: 1 | K27: 1 | L27: 1
A30: TERMINAL VALUE INPUTS
A32: Perpetuity growth rate | B32: 0.005
A33: Exit EBITDA multiple | B33: 8.5
A36: EQUITY BRIDGE INPUTS
A38: Net debt ($m) | B38: 84.62
A39: Minority interests ($m) | B39: 0
A40: Investments in associates ($m) | B40: 0
A41: Shares outstanding (m) | B41: 199

Sheet P&L
A1: P&L
A3: Year | B3: FY20 | C3: FY21 | D3: FY22 | E3: FY23 | F3: FY24 | G3: FY25 | H3: FY26 | I3: FY27 | J3: FY28 | K3: FY29 | L3: FY30
A5: Revenue | B5: 1149.2 | C5: =B5*(1+Assumptions!C23) | D5: =C5*(1+Assumptions!D23) | E5: =D5*(1+Assumptions!E23) | F5: =E5*(1+Assumptions!F23) | G5: =F5*(1+Assumptions!G23) | H5: =G5*(1+Assumptions!H23) | I5: =H5*(1+Assumptions!I23) | J5: =I5*(1+Assumptions!J23) | ... L5: =K5*(1+Assumptions!L23)
A6: EBITDA | B6: =B5*Assumptions!B24 | C6: =C5*Assumptions!C24 | D6: =D5*Assumptions!D24 | E6: =E5*Assumptions!E24 | F6: =F5*Assumptions!F24 | G6: =G5*Assumptions!G24 | H6: =H5*Assumptions!H24 | I6: =I5*Assumptions!I24 | ... L6: =L5*Assumptions!L24
A7: D&A | B7: =Assumptions!B25 | C7: =Assumptions!C25 | D7: =Assumptions!D25 | E7: =Assumptions!E25 | F7: =Assumptions!F25 | G7: =Assumptions!G25 | H7: =Assumptions!H25 | I7: =Assumptions!I25 | ... L7: =Assumptions!L25
A8: EBIT | B8: =B6+B7 | C8: =C6+C7 | D8: =D6+D7 | E8: =E6+E7 | F8: =F6+F7 | G8: =G6+G7 | H8: =H6+H7 | I8: =I6+I7 | ... L8: =L6+L7
A9: Tax on EBIT | B9: =-B8*Assumptions!$B$9 | C9: =-C8*Assumptions!$B$9 | D9: =-D8*Assumptions!$B$9 | E9: =-E8*Assumptions!$B$9 | F9: =-F8*Assumptions!$B$9 | G9: =-G8*Assumptions!$B$9 | H9: =-H8*Assumptions!$B$9 | I9: =-I8*Assumptions!$B$9 | ... L9: =-L8*Assumptions!$B$9
A10: EBIAT (NOPAT) | B10: =B8+B9 | C10: =C8+C9 | D10: =D8+D9 | E10: =E8+E9 | F10: =F8+F9 | G10: =G8+G9 | H10: =H8+H9 | I10: =I8+I9 | ... L10: =L8+L9

Sheet Valuation Calculation
A1: Valuation Calculation
A3: Year | B3: FY20 | C3: FY21 | D3: FY22 | E3: FY23 | F3: FY24 | G3: FY25 | H3: FY26 | I3: FY27 | J3: FY28 | K3: FY29 | L3: FY30
A4: Discount period | B4: 0 | C4: 1 | D4: 2 | E4: 3 | F4: 4 | G4: 5 | H4: 6 | I4: 7 | J4: 8 | K4: 9 | L4: 10
A6: EBIAT (from P&L) | B6: ='P&L'!B10 | C6: ='P&L'!C10 | D6: ='P&L'!D10 | E6: ='P&L'!E10 | F6: ='P&L'!F10 | G6: ='P&L'!G10 | H6: ='P&L'!H10 | I6: ='P&L'!I10 | ... L6: ='P&L'!L10
A7: + D&A | B7: =-'P&L'!B7 | C7: =-'P&L'!C7 | D7: =-'P&L'!D7 | E7: =-'P&L'!E7 | F7: =-'P&L'!F7 | G7: =-'P&L'!G7 | H7: =-'P&L'!H7 | I7: =-'P&L'!I7 | ... L7: =-'P&L'!L7
A8: - Capex | B8: =Assumptions!B26 | C8: =Assumptions!C26 | D8: =Assumptions!D26 | E8: =Assumptions!E26 | F8: =Assumptions!F26 | G8: =Assumptions!G26 | H8: =Assumptions!H26 | I8: =Assumptions!I26 | ... L8: =Assumptions!L26
A9: - Change in WC | B9: =-Assumptions!B27 | C9: =-Assumptions!C27 | D9: =-Assumptions!D27 | E9: =-Assumptions!E27 | F9: =-Assumptions!F27 | G9: =-Assumptions!G27 | H9: =-Assumptions!H27 | I9: =-Assumptions!I27 | ... L9: =-Assumptions!L27
A10: FCF | B10: =B6+B7+B8+B9 | C10: =C6+C7+C8+C9 | D10: =D6+D7+D8+D9 | E10: =E6+E7+E8+E9 | F10: =F6+F7+F8+F9 | G10: =G6+G7+G8+G9 | H10: =H6+H7+H8+H9 | I10: =I6+I7+I8+I9 | ... L10: =L6+L7+L8+L9
A12: Discount factor | B12: =1/(1+Assumptions!$B$17)^B4 | C12: =1/(1+Assumptions!$B$17)^C4 | D12: =1/(1+Assumptions!$B$17)^D4 | E12: =1/(1+Assumptions!$B$17)^E4 | F12: =1/(1+Assumptions!$B$17)^F4 | G12: =1/(1+Assumptions!$B$17)^G4 | H12: =1/(1+Assumptions!$B$17)^H4 | I12: =1/(1+Assumptions!$B$17)^I4 | ... L12: =1/(1+Assumptions!$B$17)^L4
A13: PV(FCF) | B13: =B10*B12 | C13: =C10*C12 | D13: =D10*D12 | E13: =E10*E12 | F13: =F10*F12 | G13: =G10*G12 | H13: =H10*H12 | I13: =I10*I12 | ... L13: =L10*L12
A15: Sum of PV(FCF) | B15: =SUM(C13:L13)
A17: Terminal value (perp) | B17: =L10*(1+Assumptions!B32)/(Assumptions!B17-Assumptions!B32)
A18: PV of TV | B18: =B17/(1+Assumptions!B17)^L4
A20: Enterprise Value | B20: =B15+B18
A22: Net debt | B22: =-Assumptions!B38
A23: Minority interests | B23: =-Assumptions!B39
A24: Investments in associates | B24: =Assumptions!B40
A25: Equity Value | B25: =B20+B22+B23+B24
A27: Shares outstanding (m) | B27: =Assumptions!B41
A28: Implied share price ($) | B28: =B25/B27
