Workbook

Sheet Assumptions
B2: Tap & Turf Holdings Pty Ltd — DCF Assumptions
B3: Project Boundary | Round 1 Indicative Bid | AUD millions
B5: Last historical FYE | C5: FY25 (Mar-25)
B6: Transaction date | C6: FY26 (Mar-26)
B8: Forecast drivers | C8: Value
B9: Revenue growth (p.a.) | C9: 0.06 | D9: p_rev_growth
B10: EBITDA margin (flat) | C10: 0.0872 | D10: p_ebitda_margin
B11: D&A / revenue | C11: 0.038 | D11: p_da_pct
B12: Capex / revenue | C12: 0.03 | D12: p_capex_pct
B13: Change in WC / revenue (outflow) | C13: 0.015 | D13: p_wc_pct
B14: Tax rate | C14: 0.19 | D14: p_tax_rate
B15: Perpetuity growth rate | C15: 0.025 | D15: p_perp_g
B16: WACC (= cost of equity, all-equity) | C16: =C31
B18: WACC build — CAPM (all-equity: net cash, asset-light)
B19: Comparable | C19: Lev β | D19: D/E | E19: Unlev β
B20: Endeavour Group | C20: 0.85 | D20: 0.35 | E20: =C20/(1+(1-$C$14)*D20)
B21: Coca-Cola Europacific | C21: 0.9 | D21: 0.5 | E21: =C21/(1+(1-$C$14)*D21)
B22: Compass Group | C22: 0.95 | D22: 0.3 | E22: =C22/(1+(1-$C$14)*D22)
B23: Aramark | C23: 1.1 | D23: 0.8 | E23: =C23/(1+(1-$C$14)*D23)
B24: Aristocrat Leisure | C24: 0.95 | D24: 0.15 | E24: =C24/(1+(1-$C$14)*D24)
B25: Average unlevered β | E25: =AVERAGE(E20:E24)
B27: Risk-free rate (AU 10Y) | C27: 0.0425
B28: Equity risk premium | C28: 0.06
B29: Specific risk premium | C29: 0.015
B30: Cost of equity (CAPM) | C30: =C27+E25*C28
B31: + Specific risk premium → WACC | C31: =C30+C29
B33: Note: valued cash-free / debt-free (net cash, no debt) → all-equity WACC, EV = equity value. No exit multiple (no comparable set in the case).

Sheet Company fin forecasts
B2: Company financial forecasts
B3: FY21–FY25 actuals · FY26–FY31 forecast (driven from Assumptions)
H4: Forecast →
B5: $m | C5: FY21 | D5: FY22 | E5: FY23 | F5: FY24 | G5: FY25 | H5: FY26 | I5: FY27 | J5: FY28 | K5: FY29 | L5: FY30 | M5: FY31
B6: Revenue | C6: 1149.23 | D6: 1255.63 | E6: 1353.84 | F6: 1446.98 | G6: 1442.62 | H6: =G6*(1+Assumptions!$C$9) | I6: =H6*(1+Assumptions!$C$9) | J6: =I6*(1+Assumptions!$C$9) | K6: =J6*(1+Assumptions!$C$9) | L6: =K6*(1+Assumptions!$C$9) | M6: =L6*(1+Assumptions!$C$9)
B7: YoY growth % | D7: =D6/C6-1 | E7: =E6/D6-1 | F7: =F6/E6-1 | G7: =G6/F6-1 | H7: =H6/G6-1 | I7: =I6/H6-1 | J7: =J6/I6-1 | K7: =K6/J6-1 | ... M7: =M6/L6-1
B8: EBITDA | C8: 94.15 | D8: 92.62 | E8: 111.8 | F8: 124.4 | G8: 127.57 | H8: =H6*Assumptions!$C$10 | I8: =I6*Assumptions!$C$10 | J8: =J6*Assumptions!$C$10 | K8: =K6*Assumptions!$C$10 | L8: =L6*Assumptions!$C$10 | M8: =M6*Assumptions!$C$10
B9: EBITDA margin % | C9: =C8/C6 | D9: =D8/D6 | E9: =E8/E6 | F9: =F8/F6 | G9: =G8/G6 | H9: =H8/H6 | I9: =I8/I6 | J9: =J8/J6 | ... M9: =M8/M6
B10: Depreciation & amortisation | C10: -36.13 | D10: -40.46 | E10: -47.2 | F10: -51.83 | G10: -54.8 | H10: =-H6*Assumptions!$C$11 | I10: =-I6*Assumptions!$C$11 | J10: =-J6*Assumptions!$C$11 | K10: =-K6*Assumptions!$C$11 | L10: =-L6*Assumptions!$C$11 | M10: =-M6*Assumptions!$C$11
B11: EBIT | C11: =C8+C10 | D11: =D8+D10 | E11: =E8+E10 | F11: =F8+F10 | G11: =G8+G10 | H11: =H8+H10 | I11: =I8+I10 | J11: =J8+J10 | ... M11: =M8+M10
B12: Tax on EBIT | C12: =-C11*Assumptions!$C$14 | D12: =-D11*Assumptions!$C$14 | E12: =-E11*Assumptions!$C$14 | F12: =-F11*Assumptions!$C$14 | G12: =-G11*Assumptions!$C$14 | H12: =-H11*Assumptions!$C$14 | I12: =-I11*Assumptions!$C$14 | J12: =-J11*Assumptions!$C$14 | ... M12: =-M11*Assumptions!$C$14
B13: Capex | C13: -36 | D13: -51 | E13: -50 | F13: -50 | G13: -50 | H13: =-H6*Assumptions!$C$12 | I13: =-I6*Assumptions!$C$12 | J13: =-J6*Assumptions!$C$12 | K13: =-K6*Assumptions!$C$12 | L13: =-L6*Assumptions!$C$12 | M13: =-M6*Assumptions!$C$12
B14: Change in working capital | C14: 0 | D14: 0 | E14: 0 | F14: 0 | G14: 0 | H14: =-H6*Assumptions!$C$13 | I14: =-I6*Assumptions!$C$13 | J14: =-J6*Assumptions!$C$13 | K14: =-K6*Assumptions!$C$13 | L14: =-L6*Assumptions!$C$13 | M14: =-M6*Assumptions!$C$13
B15: Dividend | C15: -24 | D15: -24 | E15: -24 | F15: -24 | G15: -24 | H15: -24 | I15: -24 | J15: -24 | K15: -24 | L15: -24 | M15: -24
B16: Net cash flow (post-dividend) | C16: =C8+C12+C13+C14+C15 | D16: =D8+D12+D13+D14+D15 | E16: =E8+E12+E13+E14+E15 | F16: =F8+F12+F13+F14+F15 | G16: =G8+G12+G13+G14+G15 | H16: =H8+H12+H13+H14+H15 | I16: =I8+I12+I13+I14+I15 | J16: =J8+J12+J13+J14+J15 | ... M16: =M8+M12+M13+M14+M15

Sheet DCF
B2: DCF — Perpetuity Growth (primary method)
B3: Unlevered FCF, mid-year discounting. AUD millions.
B5: $m | C5: FY26 | D5: FY27 | E5: FY28 | F5: FY29 | G5: FY30 | H5: FY31
B6: EBIT | C6: ='Company fin forecasts'!H11 | D6: ='Company fin forecasts'!I11 | E6: ='Company fin forecasts'!J11 | F6: ='Company fin forecasts'!K11 | G6: ='Company fin forecasts'!L11 | H6: ='Company fin forecasts'!M11
B7: Less: tax on EBIT | C7: =-C6*Assumptions!$C$14 | D7: =-D6*Assumptions!$C$14 | E7: =-E6*Assumptions!$C$14 | F7: =-F6*Assumptions!$C$14 | G7: =-G6*Assumptions!$C$14 | H7: =-H6*Assumptions!$C$14
B8: NOPAT | C8: =C6+C7 | D8: =D6+D7 | E8: =E6+E7 | F8: =F6+F7 | G8: =G6+G7 | H8: =H6+H7
B9: Add: D&A | C9: =-'Company fin forecasts'!H10 | D9: =-'Company fin forecasts'!I10 | E9: =-'Company fin forecasts'!J10 | F9: =-'Company fin forecasts'!K10 | G9: =-'Company fin forecasts'!L10 | H9: =-'Company fin forecasts'!M10
B10: Less: capex | C10: ='Company fin forecasts'!H13 | D10: ='Company fin forecasts'!I13 | E10: ='Company fin forecasts'!J13 | F10: ='Company fin forecasts'!K13 | G10: ='Company fin forecasts'!L13 | H10: ='Company fin forecasts'!M13
B11: Less: change in WC | C11: ='Company fin forecasts'!H14 | D11: ='Company fin forecasts'!I14 | E11: ='Company fin forecasts'!J14 | F11: ='Company fin forecasts'!K14 | G11: ='Company fin forecasts'!L14 | H11: ='Company fin forecasts'!M14
B12: Unlevered FCF | C12: =C8+C9+C10+C11 | D12: =D8+D9+D10+D11 | E12: =E8+E9+E10+E11 | F12: =F8+F9+F10+F11 | G12: =G8+G9+G10+G11 | H12: =H8+H9+H10+H11
B13: Discount period (yrs, mid-year) | C13: 0.5 | D13: 1.5 | E13: 2.5 | F13: 3.5 | G13: 4.5 | H13: 5.5
B14: Discount factor @ WACC | C14: =1/(1+Assumptions!$C$16)^C13 | D14: =1/(1+Assumptions!$C$16)^D13 | E14: =1/(1+Assumptions!$C$16)^E13 | F14: =1/(1+Assumptions!$C$16)^F13 | G14: =1/(1+Assumptions!$C$16)^G13 | H14: =1/(1+Assumptions!$C$16)^H13
B15: PV of FCF | C15: =C12*C14 | D15: =D12*D14 | E15: =E12*E14 | F15: =F12*F14 | G15: =G12*G14 | H15: =H12*H14
B17: Valuation (perpetuity growth)
B18: Sum of PV(FCF) | C18: =SUM(C15:H15)
B19: Terminal value (Gordon, undiscounted) | C19: =H12*(1+Assumptions!$C$15)/(Assumptions!$C$16-Assumptions!$C$15)
B20: PV of terminal value | C20: =C19/(1+Assumptions!$C$16)^6
B21: Enterprise value | C21: =C18+C20
B22: Net debt (cash-free/debt-free) | C22: 0
B23: Equity value (= EV) | C23: =C21-C22
B25: Check: implied EV / LFY EBITDA | C25: =C21/127.57
